zstorage/__init__.py
zstorage-0.1.6.dist-info/METADATA
zstorage-0.1.6.dist-info/WHEEL
zstorage-0.1.6.dist-info/licenses/LICENSE
zstorage-0.1.6.dist-info/RECORD
