Metadata-Version: 2.1
Name: zstorage
Version: 0.1.6
Summary: zen storage library
Project-URL: Homepage, https://github.com/inspirare6/zstorage
Project-URL: Bug Tracker, https://github.com/inspirare6/zstorage/issues
Author-email: inspirare6 <inspirare6@163.com>
License-File: LICENSE
Classifier: License :: OSI Approved :: MIT License
Classifier: Operating System :: OS Independent
Classifier: Programming Language :: Python :: 3
Requires-Python: >=3.7
Requires-Dist: minio==7.1.13
